bcirisktools/__init__.py
bcirisktools/shapley_report.py
bcirisktools/stability.py
bcirisktools/tree_crt.py
bcirisktools-0.0.12.dist-info/LICENCE
bcirisktools-0.0.12.dist-info/METADATA
bcirisktools-0.0.12.dist-info/WHEEL
bcirisktools-0.0.12.dist-info/top_level.txt
bcirisktools-0.0.12.dist-info/RECORD
